axserve/__about__.py
axserve/__init__.py
axserve/aio/__init__.py
axserve/aio/client/__init__.py
axserve/aio/client/component.py
axserve/aio/client/decorator.py
axserve/aio/client/descriptor.py
axserve/aio/client/stub.py
axserve/aio/client/stubgen.py
axserve/aio/common/__init__.py
axserve/aio/common/async_aquireable.py
axserve/aio/common/async_closeable.py
axserve/aio/common/async_closeable_queue.py
axserve/aio/common/async_connectable.py
axserve/aio/common/async_initializable.py
axserve/aio/common/async_iterable_queue.py
axserve/aio/server/__init__.py
axserve/aio/server/process.py
axserve/cli/__init__.py
axserve/client/__init__.py
axserve/client/component.py
axserve/client/decorator.py
axserve/client/descriptor.py
axserve/client/stub.py
axserve/client/stubgen.py
axserve/common/__init__.py
axserve/common/aquireable.py
axserve/common/closeable.py
axserve/common/closeable_queue.py
axserve/common/connectable.py
axserve/common/iterable_queue.py
axserve/common/logging.py
axserve/common/protocol.py
axserve/common/runnable_popen.py
axserve/common/socket.py
axserve/common/process/__init__.py
axserve/common/process/common.py
axserve/common/process/pywin32.py
axserve/common/registry/__init__.py
axserve/common/registry/common.py
axserve/common/registry/pywin32.py
axserve/proto/__init__.py
axserve/proto/active_pb2.py
axserve/proto/active_pb2.pyi
axserve/proto/active_pb2_conversion.py
axserve/proto/active_pb2_grpc.py
axserve/server/__init__.py
axserve/server/process.py
axserve/server/exe/__init__.py
axserve/server/exe/axserve-console-amd64.exe
axserve/server/exe/axserve-console-x86.exe
axserve/server/exe/axserve-win32-amd64.exe
axserve/server/exe/axserve-win32-x86.exe
axserve-0.2.0.dist-info/METADATA
axserve-0.2.0.dist-info/WHEEL
axserve-0.2.0.dist-info/entry_points.txt
axserve-0.2.0.dist-info/licenses/LICENSE
axserve-0.2.0.dist-info/RECORD
