Metadata-Version: 2.4
Name: axserve
Version: 0.2.0
Summary: AxServe python client that provides interfaces of COM or OCX components through a gRPC server.
Project-URL: Documentation, https://github.com/elbakramer/axserve#readme
Project-URL: Issues, https://github.com/elbakramer/axserve/issues
Project-URL: Source, https://github.com/elbakramer/axserve
Author-email: Yunseong Hwang <kika1492@gmail.com>
Maintainer-email: Yunseong Hwang <kika1492@gmail.com>
License-Expression: Apache-2.0
License-File: LICENSE
Keywords: activex,com,cpp,grpc,ocx,python,qt6,windows
Classifier: Development Status :: 2 - Pre-Alpha
Classifier: Environment :: Console
Classifier: Environment :: X11 Applications :: Qt
Classifier: License :: OSI Approved :: Apache Software License
Classifier: Operating System :: Microsoft :: Windows
Classifier: Operating System :: Microsoft :: Windows :: Windows 11
Classifier: Programming Language :: C++
Classifier: Programming Language :: Python
Classifier: Programming Language :: Python :: 3.10
Classifier: Programming Language :: Python :: 3.11
Classifier: Programming Language :: Python :: 3.12
Classifier: Programming Language :: Python :: Implementation :: CPython
Classifier: Programming Language :: Python :: Implementation :: PyPy
Requires-Python: >=3.10
Requires-Dist: click>=8.2.1
Requires-Dist: grpcio>=1.73.1
Requires-Dist: protobuf>=6.31.1
Requires-Dist: pywin32>=310; platform_system == 'Windows'
Requires-Dist: wrapt>=1.17.2
